.gitignore
LICENSE.md
README.md
demo.py
requirements.txt
setup.py
qtstylish/__init__.py
qtstylish/demo_widget.py
qtstylish/make_screenshots.py
qtstylish/modern_window.py
qtstylish/qtstylish.py
qtstylish.egg-info/PKG-INFO
qtstylish.egg-info/SOURCES.txt
qtstylish.egg-info/dependency_links.txt
qtstylish.egg-info/requires.txt
qtstylish.egg-info/top_level.txt
qtstylish/compiled/dark.qss
qtstylish/compiled/light.qss
qtstylish/compiled/qtstylish_rc.py
qtstylish/screenshots/dark.png
qtstylish/screenshots/light.png
qtstylish/screenshots/dark/Buttons.png
qtstylish/screenshots/dark/Containers.png
qtstylish/screenshots/dark/Controls.png
qtstylish/screenshots/dark/Displays.png
qtstylish/screenshots/dark/Inputs.png
qtstylish/screenshots/dark/Main Window.png
qtstylish/screenshots/dark/Tabs.png
qtstylish/screenshots/dark/Widgets.png
qtstylish/screenshots/light/Buttons.png
qtstylish/screenshots/light/Containers.png
qtstylish/screenshots/light/Controls.png
qtstylish/screenshots/light/Displays.png
qtstylish/screenshots/light/Inputs.png
qtstylish/screenshots/light/Main Window.png
qtstylish/screenshots/light/Tabs.png
qtstylish/screenshots/light/Widgets.png
qtstylish/stylesheets/__init__.py
qtstylish/stylesheets/dark.scss
qtstylish/stylesheets/icons.scss
qtstylish/stylesheets/light.scss
qtstylish/stylesheets/main.qrc
qtstylish/stylesheets/main.scss
qtstylish/stylesheets/resources/dark/arrow_down.svg
qtstylish/stylesheets/resources/dark/arrow_left.svg
qtstylish/stylesheets/resources/dark/arrow_right.svg
qtstylish/stylesheets/resources/dark/arrow_up.svg
qtstylish/stylesheets/resources/dark/branch_closed.svg
qtstylish/stylesheets/resources/dark/branch_end.svg
qtstylish/stylesheets/resources/dark/branch_line.svg
qtstylish/stylesheets/resources/dark/branch_more.svg
qtstylish/stylesheets/resources/dark/branch_open.svg
qtstylish/stylesheets/resources/dark/checkbox_checked.svg
qtstylish/stylesheets/resources/dark/checkbox_indeterminate.svg
qtstylish/stylesheets/resources/dark/checkbox_unchecked.svg
qtstylish/stylesheets/resources/dark/close.svg
qtstylish/stylesheets/resources/dark/line_horizontal.svg
qtstylish/stylesheets/resources/dark/line_vertical.svg
