Metadata-Version: 2.1
Name: qtstylish
Version: 0.1.5
Summary: Modern styles for PyQt5.
Home-page: https://github.com/adamerose/qtstylish
Author: Adam Rose
Author-email: adam.e.rose@hotmail.com
License: UNKNOWN
Platform: UNKNOWN
